reason/__init__.py
reason/_mixins.py
reason/_preprocess.py
reason/analysis/__init__.py
reason/analysis/_freq_dist.py
reason/classify/__init__.py
reason/classify/_classifier.py
reason/classify/_decisiontree.py
reason/classify/_knn.py
reason/classify/_naivebayes.py
reason/cluster/__init__.py
reason/cluster/_clusterer.py
reason/cluster/_dbscan.py
reason/cluster/_elbow_method.py
reason/cluster/_kmeans.py
reason/metrics/__init__.py
reason/metrics/_accuracy.py
reason/metrics/_confusion_matrix.py
reason/metrics/_distance.py
reason/ml/__init__.py
reason/ml/model.py
reason/stem/__init__.py
reason/stem/_porter.py
reason/stem/_regex.py
reason/stem/_stemmer.py
reason/tag/__init__.py
reason/tag/_default.py
reason/tag/_lookup.py
reason/tag/_pos.py
reason/tag/_pos_tagger_data.py
reason/tag/_regex.py
reason/tag/_tagger.py
reason/tokenize/__init__.py
reason/tokenize/_sent_tokenize.py
reason/tokenize/_treebank.py
reason/tokenize/_word_tokenize.py
reason/util/__init__.py
reason/util/_ngrams.py
reason-1.0.7.dist-info/LICENSE
reason-1.0.7.dist-info/METADATA
reason-1.0.7.dist-info/WHEEL
reason-1.0.7.dist-info/top_level.txt
reason-1.0.7.dist-info/RECORD
